mcp_server_fetch/__init__.py
mcp_server_fetch/__main__.py
mcp_server_fetch/server.py
allwise_mcp_fetch-2025.10.10.1248.dist-info/METADATA
allwise_mcp_fetch-2025.10.10.1248.dist-info/WHEEL
allwise_mcp_fetch-2025.10.10.1248.dist-info/entry_points.txt
allwise_mcp_fetch-2025.10.10.1248.dist-info/licenses/LICENSE
allwise_mcp_fetch-2025.10.10.1248.dist-info/RECORD
